django_cassandra_engine/__init__.py
django_cassandra_engine/apps.py
django_cassandra_engine/base/__init__.py
django_cassandra_engine/base/client.py
django_cassandra_engine/base/creation.py
django_cassandra_engine/base/features.py
django_cassandra_engine/base/introspection.py
django_cassandra_engine/base/operations.py
django_cassandra_engine/base/schema.py
django_cassandra_engine/base/validation.py
django_cassandra_engine/compat.py
django_cassandra_engine/connection.py
django_cassandra_engine/management/__init__.py
django_cassandra_engine/management/commands/__init__.py
django_cassandra_engine/management/commands/flush.py
django_cassandra_engine/management/commands/makemigrations.py
django_cassandra_engine/management/commands/migrate.py
django_cassandra_engine/management/commands/sync_cassandra.py
django_cassandra_engine/management/commands/syncdb.py
django_cassandra_engine/models/__init__.py
django_cassandra_engine/models/constants.py
django_cassandra_engine/models/django_field_methods.py
django_cassandra_engine/models/django_model_methods.py
django_cassandra_engine/rest/__init__.py
django_cassandra_engine/rest/serializers.py
django_cassandra_engine/sessions/__init__.py
django_cassandra_engine/sessions/backends/__init__.py
django_cassandra_engine/sessions/backends/cached_db.py
django_cassandra_engine/sessions/backends/db.py
django_cassandra_engine/sessions/models.py
django_cassandra_engine/test.py
django_cassandra_engine/utils.py
django_cassandra_engine-1.7.0.dist-info/LICENSE.txt
django_cassandra_engine-1.7.0.dist-info/WHEEL
django_cassandra_engine-1.7.0.dist-info/METADATA
django_cassandra_engine-1.7.0.dist-info/RECORD
