Metadata-Version: 2.1
Name: django-cassandra-engine
Version: 1.7.0
Summary: Django Cassandra Engine
Home-page: https://github.com/r4fek/django-cassandra-engine
License: 2-clause BSD
Keywords: django,cassandra,engine,backend,driver,wrapper,database,nonrel,cqlengine
Author: Rafał Furmański
Author-email: r.furmanski@gmail.com
Requires-Python: >=3.8,<4.0
Classifier: Development Status :: 5 - Production/Stable
Classifier: Environment :: Plugins
Classifier: Environment :: Web Environment
Classifier: Framework :: Django
Classifier: Intended Audience :: Developers
Classifier: License :: OSI Approved :: BSD License
Classifier: License :: Other/Proprietary License
Classifier: Operating System :: OS Independent
Classifier: Programming Language :: Python
Classifier: Programming Language :: Python :: 3
Classifier: Programming Language :: Python :: 3.10
Classifier: Programming Language :: Python :: 3.7
Classifier: Programming Language :: Python :: 3.8
Classifier: Programming Language :: Python :: 3.9
Classifier: Topic :: Database
Classifier: Topic :: Internet
Classifier: Topic :: Software Development :: Libraries :: Python Modules
Requires-Dist: django (>=2.0,<5.0)
Requires-Dist: scylla-driver (>=3.25.0,<4.0.0)
Project-URL: Changelog, https://r4fek.github.io/django-cassandra-engine/changelog/
Project-URL: Documentation, https://r4fek.github.io/django-cassandra-engine/
Project-URL: Repository, https://github.com/r4fek/django-cassandra-engine
